README.md
setup.py
src/whim/__init__.py
src/whim/__main__.py
src/whim/api.py
src/whim/cookie.py
src/whim/platform.py
src/whim/service.py
src/whim/settings.py
src/whim/whim_test.py
src/whim.egg-info/PKG-INFO
src/whim.egg-info/SOURCES.txt
src/whim.egg-info/dependency_links.txt
src/whim.egg-info/requires.txt
src/whim.egg-info/top_level.txt
src/whim.egg-info/zip-safe
src/whim/static/__init__.py
src/whim/static/alertify.min.css
src/whim/static/alertify.min.js
src/whim/static/alertify.themes.default.min.css
src/whim/static/api.js
src/whim/static/async_alerts.js
src/whim/static/editor.css
src/whim/static/editor.html
src/whim/static/favico-0.3.10.min.js
src/whim/static/favicon-180x180.png
src/whim/static/favicon-192x192.png
src/whim/static/favicon-32x32.png
src/whim/static/favicon-512x512.png
src/whim/static/licenses.html
src/whim/static/save_manager.js
src/whim/static/site.webmanifest
src/whim/static/welcome.html
src/whim/static/ace-1.4.6/LICENSE
src/whim/static/ace-1.4.6/ace.js
src/whim/static/ace-1.4.6/ext-beautify.js
src/whim/static/ace-1.4.6/ext-elastic_tabstops_lite.js
src/whim/static/ace-1.4.6/ext-emmet.js
src/whim/static/ace-1.4.6/ext-error_marker.js
src/whim/static/ace-1.4.6/ext-keybinding_menu.js
src/whim/static/ace-1.4.6/ext-language_tools.js
src/whim/static/ace-1.4.6/ext-linking.js
src/whim/static/ace-1.4.6/ext-modelist.js
src/whim/static/ace-1.4.6/ext-options.js
src/whim/static/ace-1.4.6/ext-prompt.js
src/whim/static/ace-1.4.6/ext-rtl.js
src/whim/static/ace-1.4.6/ext-searchbox.js
src/whim/static/ace-1.4.6/ext-settings_menu.js
src/whim/static/ace-1.4.6/ext-spellcheck.js
src/whim/static/ace-1.4.6/ext-split.js
src/whim/static/ace-1.4.6/ext-static_highlight.js
src/whim/static/ace-1.4.6/ext-statusbar.js
src/whim/static/ace-1.4.6/ext-textarea.js
src/whim/static/ace-1.4.6/ext-themelist.js
src/whim/static/ace-1.4.6/ext-whitespace.js
src/whim/static/ace-1.4.6/keybinding-emacs.js
src/whim/static/ace-1.4.6/keybinding-sublime.js
src/whim/static/ace-1.4.6/keybinding-vim.js
src/whim/static/ace-1.4.6/mode-abap.js
src/whim/static/ace-1.4.6/mode-abc.js
src/whim/static/ace-1.4.6/mode-actionscript.js
src/whim/static/ace-1.4.6/mode-ada.js
