Metadata-Version: 2.1
Name: whim
Version: 0.1.0a5
Summary: A simple editor
Home-page: https://github.com/Sibilance/whim
Author: Collin RM Stocks
Author-email: collinstocks@gmail.com
License: gpl-3.0
Platform: UNKNOWN
Requires-Python: >=3.6,<4
